lzdb/__init__.py
lzdb/dset.py
lzdb/groupmap.py
lzdb/keymap.py
lzdb/mpl_interaction.py
lzdb/row.py
lzdb/rows.py
lzdb/table.py
lzdb/utility.py
lzdb-0.0.11.dist-info/LICENSE
lzdb-0.0.11.dist-info/METADATA
lzdb-0.0.11.dist-info/WHEEL
lzdb-0.0.11.dist-info/top_level.txt
lzdb-0.0.11.dist-info/RECORD
