Metadata-Version: 2.1
Name: lzdb
Version: 0.0.11
Summary: An easy local database for python
Home-page: https://github.com/moenova/lazy-database
Author: moenova
Author-email: author@example.com
License: UNKNOWN
Platform: UNKNOWN
Classifier: Programming Language :: Python :: 3
Classifier: License :: OSI Approved :: MIT License
Classifier: Operating System :: OS Independent
